[
  { "title": "Task 1", "path": "Task1/index.html" },
  { "title": "Task 2", "path": "Task2/index.html" },
  { "title": "Task 3", "path": "Task3/index.html" },
  { "title": "Task 4", "path": "Task4/index.html" },
  { "title": "Task 5", "path": "Task5/index.html" },
  { "title": "Task 6", "path": "Task6/index.html" },
  { "title": "Task 7", "path": "Task7/index.html" },
  { "title": "Task 8", "path": "Task8/index.html" },
  { "title": "Task 9", "path": "Task9/index.html" },
  { "title": "Task 10", "path": "Task10/index.html" },
  { "title": "Task 11", "path": "Task11/index.html" },
  { "title": "Task 12", "path": "Task12/index.html" },
  { "title": "Task 13", "path": "Task13/index.html" },
  { "title": "Task 14A", "path": "Task14a/index.html" },
  { "title": "Task 14B", "path": "Task14b/index.html" },
  { "title": "Task 15", "path": "Task15/index.html" },
  { "title": "Task 16", "path": "Task16/index.html" }
]
